floppyforms/__init__.py
floppyforms/compat.py
floppyforms/fields.py
floppyforms/forms.py
floppyforms/models.py
floppyforms/widgets.py
floppyforms/__future__/__init__.py
floppyforms/__future__/models.py
floppyforms/gis/__init__.py
floppyforms/gis/fields.py
floppyforms/gis/widgets.py
floppyforms/static/floppyforms/gis/img/move_vertex_off.png
floppyforms/static/floppyforms/gis/img/move_vertex_on.png
floppyforms/static/floppyforms/js/MapWidget.js
floppyforms/static/floppyforms/openlayers/OpenLayers.js
floppyforms/static/floppyforms/openlayers/theme/default/google.css
floppyforms/static/floppyforms/openlayers/theme/default/ie6-style.css
floppyforms/static/floppyforms/openlayers/theme/default/style.css
floppyforms/static/floppyforms/openlayers/theme/default/style.mobile.css
floppyforms/static/floppyforms/openlayers/theme/default/img/add_point_off.png
floppyforms/static/floppyforms/openlayers/theme/default/img/add_point_on.png
floppyforms/static/floppyforms/openlayers/theme/default/img/blank.gif
floppyforms/static/floppyforms/openlayers/theme/default/img/close.gif
floppyforms/static/floppyforms/openlayers/theme/default/img/drag-rectangle-off.png
floppyforms/static/floppyforms/openlayers/theme/default/img/drag-rectangle-on.png
floppyforms/static/floppyforms/openlayers/theme/default/img/draw_line_off.png
floppyforms/static/floppyforms/openlayers/theme/default/img/draw_line_on.png
floppyforms/static/floppyforms/openlayers/theme/default/img/draw_point_off.png
floppyforms/static/floppyforms/openlayers/theme/default/img/draw_point_on.png
floppyforms/static/floppyforms/openlayers/theme/default/img/draw_polygon_off.png
floppyforms/static/floppyforms/openlayers/theme/default/img/draw_polygon_on.png
floppyforms/static/floppyforms/openlayers/theme/default/img/editing_tool_bar.png
floppyforms/static/floppyforms/openlayers/theme/default/img/move_feature_off.png
floppyforms/static/floppyforms/openlayers/theme/default/img/move_feature_on.png
django_floppyforms-1.9.0.dist-info/LICENSE
django_floppyforms-1.9.0.dist-info/METADATA
django_floppyforms-1.9.0.dist-info/WHEEL
django_floppyforms-1.9.0.dist-info/top_level.txt
django_floppyforms-1.9.0.dist-info/RECORD
