Metadata-Version: 1.1
Name: django-floppyforms
Version: 1.9.0
Summary: Full control of form rendering in the templates
Home-page: https://github.com/jazzband/django-floppyforms
Author: Gregor Müllegger
Author-email: gregor@muellegger.de
License: BSD licence, see LICENSE file
Platform: UNKNOWN
Classifier: Development Status :: 5 - Production/Stable
Classifier: Environment :: Web Environment
Classifier: Framework :: Django
Classifier: Framework :: Django :: 1.11
Classifier: Framework :: Django :: 2.1
Classifier: Intended Audience :: Developers
Classifier: License :: OSI Approved :: BSD License
Classifier: Natural Language :: English
Classifier: Programming Language :: Python
Classifier: Programming Language :: Python :: 2
Classifier: Programming Language :: Python :: 2.7
Classifier: Programming Language :: Python :: 3
Classifier: Programming Language :: Python :: 3.6
